radcad-0.14.0.dist-info/METADATA
radcad-0.14.0.dist-info/WHEEL
radcad-0.14.0.dist-info/licenses/LICENSE
radcad/.DS_Store
radcad/__init__.py
radcad/backends/__init__.py
radcad/backends/multiprocessing.py
radcad/backends/pathos.py
radcad/backends/single_process.py
radcad/compat/cadCAD/__init__.py
radcad/compat/cadCAD/configuration/__init__.py
radcad/compat/cadCAD/configuration/utils/__init__.py
radcad/compat/cadCAD/engine/__init__.py
radcad/core.py
radcad/engine.py
radcad/extensions/backends/ray.py
radcad/types.py
radcad/utils.py
radcad/wrappers.py
radcad-0.14.0.dist-info/RECORD
