Metadata-Version: 2.1
Name: radcad
Version: 0.14.0
Summary: A Python framework for designing, testing, and validating complex systems through modelling and simulation.
Author-Email: CADLabs <benschza@users.noreply.github.com>
Requires-Python: <3.13,>=3.8
Requires-Dist: pathos<1.0.0,>=0.2.7
Requires-Dist: pandas<=2.0.3; python_version < "3.9"
Requires-Dist: pandas>2.0.3; python_version >= "3.9"
Requires-Dist: py<2.0.0,>=1.11.0
Requires-Dist: numpy<1.25; python_version < "3.9"
Requires-Dist: numpy<1.26.4,>=1.25; python_version >= "3.9"
Requires-Dist: fn-py<1.0.0,>=0.6.0
Requires-Dist: cadCAD<0.5.0; python_version < "3.9" and extra == "compat"
Requires-Dist: cadCAD>=0.5.0; python_version >= "3.9" and extra == "compat"
Requires-Dist: ray<3.0.0,>=2.0.0; extra == "extension-backend-ray"
Requires-Dist: boto3<2.0.0,>=1.16.43; extra == "extension-backend-ray"
Provides-Extra: compat
Provides-Extra: extension-backend-ray
